README.rst
setup.py
pygeon/__init__.py
pygeon/api.py
pygeon/model.py
pygeon/parser.py
pygeon/store.py
pygeon/utils.py
pygeon.egg-info/PKG-INFO
pygeon.egg-info/SOURCES.txt
pygeon.egg-info/dependency_links.txt
pygeon.egg-info/requires.txt
pygeon.egg-info/top_level.txt
scripts/pygeon