Metadata-Version: 1.1
Name: pygeon
Version: 0.1.0
Summary: IP Geolocation in Python
Home-page: http://bitbucket.org/al45tair/pygeon
Author: Alastair Houghton
Author-email: alastair@alastairs-place.net
License: MIT License
Platform: UNKNOWN
Classifier: Development Status :: 4 - Beta
Classifier: License :: OSI Approved :: MIT License
Classifier: Topic :: Software Development :: Libraries
Classifier: Topic :: System :: Networking
Provides: pygeon
